mulambda/__init__.py
mulambda/context.py
mulambda/example_usecase.py
mulambda/util.py
mulambda/api/__init__.py
mulambda/api/serve.py
mulambda/local/executor.py
mulambda/models/__init__.py
mulambda/models/executor.py
mulambda/models/matching.py
mulambda/models/registry.py
mulambda/openai/executor.py
mulambda-0.0.1.dist-info/LICENSE
mulambda-0.0.1.dist-info/METADATA
mulambda-0.0.1.dist-info/WHEEL
mulambda-0.0.1.dist-info/entry_points.txt
mulambda-0.0.1.dist-info/top_level.txt
mulambda-0.0.1.dist-info/RECORD
