Metadata-Version: 2.1
Name: mulambda
Version: 0.0.1
Summary: A Serverless Platform for Automated Machine Learning
Author-email: Silvio Vasiljevic <silvio.vasiljevic@gmail.com>
Requires-Python: >=3.11
License-File: LICENSE
Requires-Dist: numpy
Requires-Dist: typer
Requires-Dist: openai
Provides-Extra: dev
Requires-Dist: pytest ; extra == 'dev'
Requires-Dist: black ; extra == 'dev'
Requires-Dist: ruff ; extra == 'dev'
Requires-Dist: pre-commit ; extra == 'dev'
